Workbook

Sheet Full Roster
A1: Sale Rep ID | B1: Full Contact ID | C1: First Name | D1: Last Name | E1: Full Name | F1: Representative Category | G1: YJ Category | H1: Active | I1: Sales team | J1: Phone Number | K1: Email | L1: Company - Job | M1: 25-26 Dollars | N1: Future Class | O1: In SF
A2: 2041793 | B2: 0031Y0000637jKFQAY | C2: Bob | D2: Aggarwal | E2: Bob Aggarwal | F2: Yellow Jacket | G2: Committee Member | H2: TRUE | I2: Peter the Anteater | J2: 480-323-0560 | K2: baggarwal@alliancebankofarizona.com | L2: Alliance Bank-VP Commercial Banking | M2: {=XLOOKUP(C2&D2, 'Yellow Jacket Fundraising 25-26'!$A$2:$A$112 & 'Yellow Jacket Fundraising 25-26'!$B$2:$B$112, 'Yellow Jacket Fundraising 25-26'!$G$2:$G$112, "Not Found")} -> 20112 | N2: 2021-22 | O2: =vlookup(B2,'SF Roster'!A:G,7,false) -> Committee Member
A3: 2138132 | C3: Daniel | D3: Akmon | E3: Daniel Akmon | F3: Yellow Jacket | G3: Future | H3: TRUE | I3: Fightin' Artichokes | J3: (602) 361-4600 | K3: Daniel.akmon@claconnect.com | L3: CLA-Principal | M3: {=XLOOKUP(C3&D3, 'Yellow Jacket Fundraising 25-26'!$A$2:$A$112 & 'Yellow Jacket Fundraising 25-26'!$B$2:$B$112, 'Yellow Jacket Fundraising 25-26'!$G$2:$G$112, "Not Found")} -> Future | N3: 2026-27 | O3: =vlookup(B3,'SF Roster'!A:G,7,false) -> #N/A
A4: 2041775 | B4: 0031Y0000637jiWQAQ | C4: Jonathan | D4: Amato | E4: Jonathan Amato | F4: Yellow Jacket | G4: Committee Member | H4: TRUE | I4: Blue Hose | J4: 914-494-3179 | K4: jonathan.amato@westin.com | L4: The Westin Kierland Resort & Spa - Director of Sales and Marketing | M4: {=XLOOKUP(C4&D4, 'Yellow Jacket Fundraising 25-26'!$A$2:$A$112 & 'Yellow Jacket Fundraising 25-26'!$B$2:$B$112, 'Yellow Jacket Fundraising 25-26'!$G$2:$G$112, "Not Found")} -> 46431 | N4: 2020-21 | O4: =vlookup(B4,'SF Roster'!A:G,7,false) -> Committee Member
A5: 93126 | B5: 0035d00006NTQsiAAH | C5: Jeffrey | D5: Anderson | E5: Jeffrey Anderson | F5: Yellow Jacket | G5: Committee Member | H5: TRUE | I5: Banana Slugs | J5: (602) 321-9660 | K5: Jeff.anderson@aleragroup.com | L5: BCG 401(k) Advisors - President | M5: {=XLOOKUP(C5&D5, 'Yellow Jacket Fundraising 25-26'!$A$2:$A$112 & 'Yellow Jacket Fundraising 25-26'!$B$2:$B$112, 'Yellow Jacket Fundraising 25-26'!$G$2:$G$112, "Not Found")} -> 39259 | N5: 2021-22 | O5: =vlookup(B5,'SF Roster'!A:G,7,false) -> Committee Member
A6: 2095489 | C6: Ray | D6: Artigue | E6: Ray Artigue | F6: Life Directors & Members | G6: Life Director | H6: TRUE | J6: N/A | K6: N/A | L6: N/A | M6: {=XLOOKUP(C6&D6, 'Yellow Jacket Fundraising 25-26'!$A$2:$A$112 & 'Yellow Jacket Fundraising 25-26'!$B$2:$B$112, 'Yellow Jacket Fundraising 25-26'!$G$2:$G$112, "Not Found")} -> Not Found | N6: N/A | O6: =vlookup(B6,'SF Roster'!A:G,7,false) -> #N/A
A7: 2138133 | C7: Chancellor | D7: Barjona | E7: Chancellor Barjona | F7: Yellow Jacket | G7: Future | H7: TRUE | I7: Peter the Anteater | J7: (480) 599-9198 | K7: chancellor.barjona@gmail.com | L7: IBM Principle Data & AI Leader - Financial Services | M7: {=XLOOKUP(C7&D7, 'Yellow Jacket Fundraising 25-26'!$A$2:$A$112 & 'Yellow Jacket Fundraising 25-26'!$B$2:$B$112, 'Yellow Jacket Fundraising 25-26'!$G$2:$G$112, "Not Found")} -> Future | N7: 2026-27 | O7: =vlookup(B7,'SF Roster'!A:G,7,false) -> #N/A
A8: 79594 | C8: Patrick | D8: Barkley | E8: Patrick Barkley | F8: Life Directors & Members | G8: Life Director | H8: TRUE | J8: N/A | K8: N/A | L8: N/A | M8: {=XLOOKUP(C8&D8, 'Yellow Jacket Fundraising 25-26'!$A$2:$A$112 & 'Yellow Jacket Fundraising 25-26'!$B$2:$B$112, 'Yellow Jacket Fundraising 25-26'!$G$2:$G$112, "Not Found")} -> Not Found | N8: N/A | O8: =vlookup(B8,'SF Roster'!A:G,7,false) -> #N/A
A9: 2041805 | B9: 003i000000HAUd8AAH | C9: Eric | D9: Barkyoumb | E9: Eric Barkyoumb | F9: Yellow Jacket | G9: Committee Member | H9: TRUE | I9: Dirtbags | J9: 480-209-7993 | K9: ebarkyoumb@gmail.com | L9: Dignity Health Foundation - Philanthropy Manager | M9: {=XLOOKUP(C9&D9, 'Yellow Jacket Fundraising 25-26'!$A$2:$A$112 & 'Yellow Jacket Fundraising 25-26'!$B$2:$B$112, 'Yellow Jacket Fundraising 25-26'!$G$2:$G$112, "Not Found")} -> 115548 | N9: 2012-13 | O9: =vlookup(B9,'SF Roster'!A:G,7,false) -> Committee Member
A10: 2095186 | C10: Brian | D10: Bednar | E10: Brian Bednar | F10: Board of Directors | G10: Board | H10: TRUE | J10: N/A | K10: N/A | L10: N/A | M10: {=XLOOKUP(C10&D10, 'Yellow Jacket Fundraising 25-26'!$A$2:$A$112 & 'Yellow Jacket Fundraising 25-26'!$B$2:$B$112, 'Yellow Jacket Fundraising 25-26'!$G$2:$G$112, "Not Found")} -> Not Found | N10: N/A | O10: =vlookup(B10,'SF Roster'!A:G,7,false) -> #N/A
A11: 2095195 | C11: Judy | D11: Bernas | E11: Judy Bernas | F11: Board of Directors | G11: Board | H11: TRUE | J11: N/A | K11: N/A | L11: N/A | M11: {=XLOOKUP(C11&D11, 'Yellow Jacket Fundraising 25-26'!$A$2:$A$112 & 'Yellow Jacket Fundraising 25-26'!$B$2:$B$112, 'Yellow Jacket Fundraising 25-26'!$G$2:$G$112, "Not Found")} -> Not Found | N11: N/A | O11: =vlookup(B11,'SF Roster'!A:G,7,false) -> #N/A
A12: 100553 | C12: Scott | D12: Bernstein | E12: Scott Bernstein | F12: Life Directors & Members | G12: Life Member | H12: TRUE | J12: N/A | K12: N/A | L12: N/A | M12: {=XLOOKUP(C12&D12, 'Yellow Jacket Fundraising 25-26'!$A$2:$A$112 & 'Yellow Jacket Fundraising 25-26'!$B$2:$B$112, 'Yellow Jacket Fundraising 25-26'!$G$2:$G$112, "Not Found")} -> Not Found | N12: N/A | O12: =vlookup(B12,'SF Roster'!A:G,7,false) -> #N/A
A13: 2041802 | C13: Bryan | D13: Beverly | E13: Bryan Beverly | F13: Life Directors & Members | G13: Life Member | H13: TRUE | J13: N/A | K13: N/A | L13: N/A | M13: {=XLOOKUP(C13&D13, 'Yellow Jacket Fundraising 25-26'!$A$2:$A$112 & 'Yellow Jacket Fundraising 25-26'!$B$2:$B$112, 'Yellow Jacket Fundraising 25-26'!$G$2:$G$112, "Not Found")} -> Not Found | N13: N/A | O13: =vlookup(B13,'SF Roster'!A:G,7,false) -> #N/A
A14: 2095193 | C14: Jeff | D14: Beyersdorfer | E14: Jeff Beyersdorfer | F14: Board of Directors | G14: Board | H14: TRUE | J14: N/A | K14: N/A | L14: N/A | M14: {=XLOOKUP(C14&D14, 'Yellow Jacket Fundraising 25-26'!$A$2:$A$112 & 'Yellow Jacket Fundraising 25-26'!$B$2:$B$112, 'Yellow Jacket Fundraising 25-26'!$G$2:$G$112, "Not Found")} -> Not Found | N14: N/A | O14: =vlookup(B14,'SF Roster'!A:G,7,false) -> #N/A
A15: 2041836 | B15: 0035d00006iGLA8AAO | C15: Warren | D15: Black | E15: Warren Black | F15: Yellow Jacket | G15: Committee Member | H15: TRUE | I15: Cobbers | J15: 480-285-8502 | K15: warren.c.black@outlook.com | L15: Merrill Lynch - Financial Advisor Senior Portfolio Advisor | M15: {=XLOOKUP(C15&D15, 'Yellow Jacket Fundraising 25-26'!$A$2:$A$112 & 'Yellow Jacket Fundraising 25-26'!$B$2:$B$112, 'Yellow Jacket Fundraising 25-26'!$G$2:$G$112, "Not Found")} -> 19523 | N15: 2022-23 | O15: =vlookup(B15,'SF Roster'!A:G,7,false) -> Committee Member
A16: 2044787 | C16: Lisa | D16: Borowsky | E16: Lisa Borowsky | F16: Yellow Jacket | H16: FALSE | J16: N/A | K16: N/A | L16: N/A | M16: {=XLOOKUP(C16&D16, 'Yellow Jacket Fundraising 25-26'!$A$2:$A$112 & 'Yellow Jacket Fundraising 25-26'!$B$2:$B$112, 'Yellow Jacket Fundraising 25-26'!$G$2:$G$112, "Not Found")} -> Not Found | N16: N/A | O16: =vlookup(B16,'SF Roster'!A:G,7,false) -> #N/A
A17: 2044788 | B17: 0035d0000793oC6AAI | C17: Bryan | D17: Boyer | E17: Bryan Boyer | F17: Yellow Jacket | G17: Committee Member | H17: TRUE | I17: Pistol Petes | J17: 480-267-4169 | K17: bboyer7740@gmail.com | L17: Avis/Budget Group - Business Development Manager | M17: {=XLOOKUP(C17&D17, 'Yellow Jacket Fundraising 25-26'!$A$2:$A$112 & 'Yellow Jacket Fundraising 25-26'!$B$2:$B$112, 'Yellow Jacket Fundraising 25-26'!$G$2:$G$112, "Not Found")} -> 8493 | N17: 2023-24 | O17: =vlookup(B17,'SF Roster'!A:G,7,false) -> Committee Member
A18: 2041858 | C18: Damon | D18: Boze | E18: Damon Boze | F18: Yellow Jacket | H18: FALSE | J18: N/A | K18: N/A | L18: N/A | M18: {=XLOOKUP(C18&D18, 'Yellow Jacket Fundraising 25-26'!$A$2:$A$112 & 'Yellow Jacket Fundraising 25-26'!$B$2:$B$112, 'Yellow Jacket Fundraising 25-26'!$G$2:$G$112, "Not Found")} -> Not Found | N18: N/A | O18: =vlookup(B18,'SF Roster'!A:G,7,false) -> #N/A
A19: 105682 | B19: 0035d00006iGLX7AAO | C19: Justin | D19: Bretag | E19: Justin Bretag | F19: Yellow Jacket | G19: Committee Member | H19: TRUE | I19: Fighting Pickles | J19: (602) 361-7027 | K19: Justin.bretag@busey.com | L19: Busey Bank-Managing Director Commercial | M19: {=XLOOKUP(C19&D19, 'Yellow Jacket Fundraising 25-26'!$A$2:$A$112 & 'Yellow Jacket Fundraising 25-26'!$B$2:$B$112, 'Yellow Jacket Fundraising 25-26'!$G$2:$G$112, "Not Found")} -> 50127 | N19: 2022-23 | O19: =vlookup(B19,'SF Roster'!A:G,7,false) -> Committee Member
A20: 97581 | C20: Robert | D20: Bridge | E20: Robert Bridge | F20: Life Directors & Members | G20: Life Member | H20: TRUE | J20: N/A | K20: N/A | L20: N/A | M20: {=XLOOKUP(C20&D20, 'Yellow Jacket Fundraising 25-26'!$A$2:$A$112 & 'Yellow Jacket Fundraising 25-26'!$B$2:$B$112, 'Yellow Jacket Fundraising 25-26'!$G$2:$G$112, "Not Found")} -> Not Found | N20: N/A | O20: =vlookup(B20,'SF Roster'!A:G,7,false) -> #N/A
A21: 2044789 | C21: Martyn | D21: Bridgeman | E21: Martyn Bridgeman | F21: Yellow Jacket | H21: FALSE | J21: N/A | K21: N/A | L21: N/A | M21: {=XLOOKUP(C21&D21, 'Yellow Jacket Fundraising 25-26'!$A$2:$A$112 & 'Yellow Jacket Fundraising 25-26'!$B$2:$B$112, 'Yellow Jacket Fundraising 25-26'!$G$2:$G$112, "Not Found")} -> Not Found | N21: N/A | O21: =vlookup(B21,'SF Roster'!A:G,7,false) -> #N/A
A22: 2044790 | B22: 0035d0000793o4ZAAQ | C22: Lindsey | D22: Brist | E22: Lindsey Brist | F22: Yellow Jacket | G22: Committee Member | H22: TRUE | I22: Stormy Petrels | J22: (208) 631-7601 | K22: lindsey.brist@mmrgrp.com | L22: MMR Constructors - Business Development Manager | M22: {=XLOOKUP(C22&D22, 'Yellow Jacket Fundraising 25-26'!$A$2:$A$112 & 'Yellow Jacket Fundraising 25-26'!$B$2:$B$112, 'Yellow Jacket Fundraising 25-26'!$G$2:$G$112, "Not Found")} -> 27359 | N22: 2023-24 | O22: =vlookup(B22,'SF Roster'!A:G,7,false) -> Committee Member
A23: 2095202 | C23: Tim | D23: Brown | E23: Tim Brown | F23: Board of Directors | G23: Board | H23: TRUE | J23: N/A | K23: N/A | L23: N/A | M23: {=XLOOKUP(C23&D23, 'Yellow Jacket Fundraising 25-26'!$A$2:$A$112 & 'Yellow Jacket Fundraising 25-26'!$B$2:$B$112, 'Yellow Jacket Fundraising 25-26'!$G$2:$G$112, "Not Found")} -> Not Found | N23: N/A | O23: =vlookup(B23,'SF Roster'!A:G,7,false) -> #N/A
A24: 2138142 | C24: Lisa | D24: Bullington | E24: Lisa Bullington | F24: Board of Directors | G24: Board | H24: TRUE | J24: N/A | K24: N/A | L24: N/A | M24: {=XLOOKUP(C24&D24, 'Yellow Jacket Fundraising 25-26'!$A$2:$A$112 & 'Yellow Jacket Fundraising 25-26'!$B$2:$B$112, 'Yellow Jacket Fundraising 25-26'!$G$2:$G$112, "Not Found")} -> Not Found | N24: N/A | O24: =vlookup(B24,'SF Roster'!A:G,7,false) -> #N/A
A25: 100695 | B25: 0031Y00005kTGeIQAW | C25: Taylor | D25: Burgoon | E25: Taylor Burgoon | F25: Yellow Jacket | G25: Committee Member | H25: TRUE | I25: Fightin' Artichokes | J25: 734-776-7362 | K25: tburgoon@fennemorelaw.com | L25: Fennemore Craig P.C. Attorney | M25: {=XLOOKUP(C25&D25, 'Yellow Jacket Fundraising 25-26'!$A$2:$A$112 & 'Yellow Jacket Fundraising 25-26'!$B$2:$B$112, 'Yellow Jacket Fundraising 25-26'!$G$2:$G$112, "Not Found")} -> 14319 | N25: 2019-20 | O25: =vlookup(B25,'SF Roster'!A:G,7,false) -> Committee Member
A26: 2041835 | B26: 0035d00006iGLXqAAO | C26: Benjamin | D26: Burke | E26: Benjamin Burke | F26: Yellow Jacket | G26: Committee Member | H26: TRUE | I26: Banana Slugs | J26: 608-385-4078 | K26: benburke@msn.com | L26: Van Wagner-Vice President College Division | M26: {=XLOOKUP(C26&D26, 'Yellow Jacket Fundraising 25-26'!$A$2:$A$112 & 'Yellow Jacket Fundraising 25-26'!$B$2:$B$112, 'Yellow Jacket Fundraising 25-26'!$G$2:$G$112, "Not Found")} -> 8158 | N26: 2022-23 | O26: =vlookup(B26,'SF Roster'!A:G,7,false) -> Committee Member
A27: 2138160 | C27: Tyler | D27: Butler | E27: Tyler Butler | F27: Yellow Jacket | G27: Future | H27: TRUE | I27: Dirtbags | J27: (480) 431-8580 | K27: connect@collaborationforgood.com | L27: Collaboration for Good Founder | M27: {=XLOOKUP(C27&D27, 'Yellow Jacket Fundraising 25-26'!$A$2:$A$112 & 'Yellow Jacket Fundraising 25-26'!$B$2:$B$112, 'Yellow Jacket Fundraising 25-26'!$G$2:$G$112, "Not Found")} -> Future | N27: 2026-27 | O27: =vlookup(B27,'SF Roster'!A:G,7,false) -> #N/A
A28: 2041837 | C28: Jake | D28: Butterfield | E28: Jake Butterfield | F28: Yellow Jacket | H28: FALSE | J28: N/A | K28: N/A | L28: N/A | M28: {=XLOOKUP(C28&D28, 'Yellow Jacket Fundraising 25-26'!$A$2:$A$112 & 'Yellow Jacket Fundraising 25-26'!$B$2:$B$112, 'Yellow Jacket Fundraising 25-26'!$G$2:$G$112, "Not Found")} -> Not Found | N28: N/A | O28: =vlookup(B28,'SF Roster'!A:G,7,false) -> #N/A
A29: 2095205 | C29: Greg | D29: Byrne | E29: Greg Byrne | F29: Board of Directors | G29: Board | H29: TRUE | J29: N/A | K29: N/A | L29: N/A | M29: {=XLOOKUP(C29&D29, 'Yellow Jacket Fundraising 25-26'!$A$2:$A$112 & 'Yellow Jacket Fundraising 25-26'!$B$2:$B$112, 'Yellow Jacket Fundraising 25-26'!$G$2:$G$112, "Not Found")} -> Not Found | N29: N/A | O29: =vlookup(B29,'SF Roster'!A:G,7,false) -> #N/A
A30: 2041838 | C30: Joe | D30: Cafferelli | E30: Joe Cafferelli | F30: Life Directors & Members | G30: Life Member | H30: TRUE | J30: N/A | K30: N/A | L30: N/A | M30: {=XLOOKUP(C30&D30, 'Yellow Jacket Fundraising 25-26'!$A$2:$A$112 & 'Yellow Jacket Fundraising 25-26'!$B$2:$B$112, 'Yellow Jacket Fundraising 25-26'!$G$2:$G$112, "Not Found")} -> Not Found | N30: N/A | O30: =vlookup(B30,'SF Roster'!A:G,7,false) -> #N/A
A31: 2062813 | B31: 003VX00000CeOJGYA3 | C31: Ben | D31: Calacci | E31: Ben Calacci | F31: Yellow Jacket | G31: Committee Member | H31: TRUE | I31: Banana Slugs | J31: (703) 967-7691 | K31: ben.calacci@gmail.com | L31: Team Velocity - Vice President OEM | M31: {=XLOOKUP(C31&D31, 'Yellow Jacket Fundraising 25-26'!$A$2:$A$112 & 'Yellow Jacket Fundraising 25-26'!$B$2:$B$112, 'Yellow Jacket Fundraising 25-26'!$G$2:$G$112, "Not Found")} -> 20034 | N31: 2024-25 | O31: =vlookup(B31,'SF Roster'!A:G,7,false) -> Committee Member
A32: 2041855 | C32: Grady | D32: Callaghan | E32: Grady Callaghan | F32: Yellow Jacket | H32: FALSE | J32: N/A | K32: N/A | L32: N/A | M32: {=XLOOKUP(C32&D32, 'Yellow Jacket Fundraising 25-26'!$A$2:$A$112 & 'Yellow Jacket Fundraising 25-26'!$B$2:$B$112, 'Yellow Jacket Fundraising 25-26'!$G$2:$G$112, "Not Found")} -> Not Found | N32: N/A | O32: =vlookup(B32,'SF Roster'!A:G,7,false) -> #N/A
A33: 2095088 | C33: Brett | D33: Callahan | E33: Brett Callahan | F33: Yellow Jacket | H33: FALSE | J33: N/A | K33: N/A | L33: N/A | M33: {=XLOOKUP(C33&D33, 'Yellow Jacket Fundraising 25-26'!$A$2:$A$112 & 'Yellow Jacket Fundraising 25-26'!$B$2:$B$112, 'Yellow Jacket Fundraising 25-26'!$G$2:$G$112, "Not Found")} -> Not Found | N33: N/A | O33: =vlookup(B33,'SF Roster'!A:G,7,false) -> #N/A
A34: 2041783 | C34: Jennifer | D34: Cannon | E34: Jennifer Cannon | F34: Life Directors & Members | G34: Life Member | H34: TRUE | J34: N/A | K34: N/A | L34: N/A | M34: {=XLOOKUP(C34&D34, 'Yellow Jacket Fundraising 25-26'!$A$2:$A$112 & 'Yellow Jacket Fundraising 25-26'!$B$2:$B$112, 'Yellow Jacket Fundraising 25-26'!$G$2:$G$112, "Not Found")} -> Not Found | N34: N/A | O34: =vlookup(B34,'SF Roster'!A:G,7,false) -> #N/A
A35: 101859 | C35: Gene | D35: Carl | E35: Gene Carl | F35: Life Directors & Members | G35: Life Member | H35: TRUE | J35: N/A | K35: N/A | L35: N/A | M35: {=XLOOKUP(C35&D35, 'Yellow Jacket Fundraising 25-26'!$A$2:$A$112 & 'Yellow Jacket Fundraising 25-26'!$B$2:$B$112, 'Yellow Jacket Fundraising 25-26'!$G$2:$G$112, "Not Found")} -> Not Found | N35: N/A | O35: =vlookup(B35,'SF Roster'!A:G,7,false) -> #N/A
A36: 2044792 | C36: Eric | D36: Caruth | E36: Eric Caruth | F36: Yellow Jacket | H36: FALSE | J36: N/A | K36: N/A | L36: N/A | M36: {=XLOOKUP(C36&D36, 'Yellow Jacket Fundraising 25-26'!$A$2:$A$112 & 'Yellow Jacket Fundraising 25-26'!$B$2:$B$112, 'Yellow Jacket Fundraising 25-26'!$G$2:$G$112, "Not Found")} -> Not Found | N36: N/A | O36: =vlookup(B36,'SF Roster'!A:G,7,false) -> #N/A
A37: 2044793 | C37: Izabela | D37: Castillo | E37: Izabela Castillo | F37: Yellow Jacket | H37: FALSE | J37: N/A | K37: N/A | L37: N/A | M37: {=XLOOKUP(C37&D37, 'Yellow Jacket Fundraising 25-26'!$A$2:$A$112 & 'Yellow Jacket Fundraising 25-26'!$B$2:$B$112, 'Yellow Jacket Fundraising 25-26'!$G$2:$G$112, "Not Found")} -> Not Found | N37: N/A | O37: =vlookup(B37,'SF Roster'!A:G,7,false) -> #N/A
A38: 2041857 | C38: John | D38: Craiger | E38: John Craiger | F38: Life Directors & Members | G38: Life Member | H38: TRUE | J38: N/A | K38: N/A | L38: N/A | M38: {=XLOOKUP(C38&D38, 'Yellow Jacket Fundraising 25-26'!$A$2:$A$112 & 'Yellow Jacket Fundraising 25-26'!$B$2:$B$112, 'Yellow Jacket Fundraising 25-26'!$G$2:$G$112, "Not Found")} -> Not Found | N38: N/A | O38: =vlookup(B38,'SF Roster'!A:G,7,false) -> #N/A
A39: 2041823 | C39: Walker | D39: Crowson | E39: Walker Crowson | F39: Life Directors & Members | G39: Life Member | H39: TRUE | J39: N/A | K39: N/A | L39: N/A | M39: {=XLOOKUP(C39&D39, 'Yellow Jacket Fundraising 25-26'!$A$2:$A$112 & 'Yellow Jacket Fundraising 25-26'!$B$2:$B$112, 'Yellow Jacket Fundraising 25-26'!$G$2:$G$112, "Not Found")} -> Not Found | N39: N/A | O39: =vlookup(B39,'SF Roster'!A:G,7,false) -> #N/A
A40: 2095089 | B40: 003VX00000YQJzdYAH | C40: Kerri | D40: Cummiskey | E40: Kerri Cummiskey | F40: Yellow Jacket | G40: Committee Member | H40: TRUE | I40: Cobbers | J40: (480) 435-5347 | K40: kerri.cummiskey@alumus.com | L40: Alumus Sr VP of Network Development and Strategic Partnerships | M40: {=XLOOKUP(C40&D40, 'Yellow Jacket Fundraising 25-26'!$A$2:$A$112 & 'Yellow Jacket Fundraising 25-26'!$B$2:$B$112, 'Yellow Jacket Fundraising 25-26'!$G$2:$G$112, "Not Found")} -> 11002 | N40: 2025-26 | O40: =vlookup(B40,'SF Roster'!A:G,7,false) -> Committee Member
A41: 2041820 | B41: 0035d00006NTR3CAAX | C41: Patrick | D41: Davis | E41: Patrick Davis | F41: Yellow Jacket | G41: Committee Member | H41: TRUE | I41: Gorlocks | J41: 480-980-3407 | K41: patrick@davisconsultgroup.net | L41: Urban Luxe Real Estate - Real Estate Agent | M41: {=XLOOKUP(C41&D41, 'Yellow Jacket Fundraising 25-26'!$A$2:$A$112 & 'Yellow Jacket Fundraising 25-26'!$B$2:$B$112, 'Yellow Jacket Fundraising 25-26'!$G$2:$G$112, "Not Found")} -> 10733 | N41: 2021-22 | O41: =vlookup(B41,'SF Roster'!A:G,7,false) -> Committee Member
A42: 2044794 | B42: 0035d0000793ntKAAQ | C42: Steven | D42: Davis | E42: Steven Davis | F42: Yellow Jacket | G42: Committee Member | H42: TRUE | I42: Pistol Petes | J42: (602) 284-8681 | K42: Steven@RdEnterprisesaz.com | L42: RD Enterprises - Managing Partner | M42: {=XLOOKUP(C42&D42, 'Yellow Jacket Fundraising 25-26'!$A$2:$A$112 & 'Yellow Jacket Fundraising 25-26'!$B$2:$B$112, 'Yellow Jacket Fundraising 25-26'!$G$2:$G$112, "Not Found")} -> 7711 | N42: 2023-24 | O42: =vlookup(B42,'SF Roster'!A:G,7,false) -> Committee Member
A43: 2041840 | B43: 003i000004UDMfrAAH | C43: Brian | D43: Debnam | E43: Brian Debnam | F43: Yellow Jacket | G43: Committee Member | H43: TRUE | I43: Fighting Pickles | J43: (520) 990-7030 | K43: bkdebnam@gmail.com | L43: NIKE Inc-Director & Chief of Staff Global Footwear Product Creation | M43: {=XLOOKUP(C43&D43, 'Yellow Jacket Fundraising 25-26'!$A$2:$A$112 & 'Yellow Jacket Fundraising 25-26'!$B$2:$B$112, 'Yellow Jacket Fundraising 25-26'!$G$2:$G$112, "Not Found")} -> 20642 | N43: 2017-18 | O43: =vlookup(B43,'SF Roster'!A:G,7,false) -> Committee Member
A44: 2041826 | B44: 0031Y0000637jzwQAA | C44: Ryan | D44: Delaney | E44: Ryan Delaney | F44: Yellow Jacket | G44: Committee Member | H44: TRUE | I44: Fightin' Artichokes | J44: 319-470-3845 | K44: ryan.delaney@busey.com | L44: Busey Bank - Senior VP Director of Middle Market Banking | M44: {=XLOOKUP(C44&D44, 'Yellow Jacket Fundraising 25-26'!$A$2:$A$112 & 'Yellow Jacket Fundraising 25-26'!$B$2:$B$112, 'Yellow Jacket Fundraising 25-26'!$G$2:$G$112, "Not Found")} -> 38690 | N44: 2020-21 | O44: =vlookup(B44,'SF Roster'!A:G,7,false) -> Committee Member
A45: 2041839 | C45: Jason | D45: DeLuigi | E45: Jason DeLuigi | F45: Yellow Jacket | H45: FALSE | J45: N/A | K45: N/A | L45: N/A | M45: {=XLOOKUP(C45&D45, 'Yellow Jacket Fundraising 25-26'!$A$2:$A$112 & 'Yellow Jacket Fundraising 25-26'!$B$2:$B$112, 'Yellow Jacket Fundraising 25-26'!$G$2:$G$112, "Not Found")} -> Not Found | N45: N/A | O45: =vlookup(B45,'SF Roster'!A:G,7,false) -> #N/A
A46: 2044795 | C46: BJ | D46: Denker | E46: BJ Denker | F46: Yellow Jacket | H46: FALSE | J46: N/A | K46: N/A | L46: N/A | M46: {=XLOOKUP(C46&D46, 'Yellow Jacket Fundraising 25-26'!$A$2:$A$112 & 'Yellow Jacket Fundraising 25-26'!$B$2:$B$112, 'Yellow Jacket Fundraising 25-26'!$G$2:$G$112, "Not Found")} -> Not Found | N46: N/A | O46: =vlookup(B46,'SF Roster'!A:G,7,false) -> #N/A
A47: 2138161 | C47: Sarah | D47: Desmond | E47: Sarah Desmond | F47: Yellow Jacket | G47: Future | H47: TRUE | I47: Peter the Anteater | J47: (602) 826-8866 | K47: sarah.desmond@ubs.com | L47: UBS/Financial Advisor | M47: {=XLOOKUP(C47&D47, 'Yellow Jacket Fundraising 25-26'!$A$2:$A$112 & 'Yellow Jacket Fundraising 25-26'!$B$2:$B$112, 'Yellow Jacket Fundraising 25-26'!$G$2:$G$112, "Not Found")} -> Future | N47: 2026-27 | O47: =vlookup(B47,'SF Roster'!A:G,7,false) -> #N/A
A48: 2062814 | B48: 003VX00000CfFFVYA3 | C48: David | D48: Dobrusin | E48: David Dobrusin | F48: Yellow Jacket | G48: Committee Member | H48: TRUE | I48: Fighting Camels | J48: (602) 369-9716 | K48: ddobrusin@gmail.com | L48: Dobrusin Financial LLC - President | M48: {=XLOOKUP(C48&D48, 'Yellow Jacket Fundraising 25-26'!$A$2:$A$112 & 'Yellow Jacket Fundraising 25-26'!$B$2:$B$112, 'Yellow Jacket Fundraising 25-26'!$G$2:$G$112, "Not Found")} -> 800 | N48: 2024-25 | O48: =vlookup(B48,'SF Roster'!A:G,7,false) -> Committee Member
A49: 2041806 | C49: Dave | D49: Dorward | E49: Dave Dorward | F49: Board of Directors | G49: Board | H49: TRUE | J49: N/A | K49: N/A | L49: N/A | M49: {=XLOOKUP(C49&D49, 'Yellow Jacket Fundraising 25-26'!$A$2:$A$112 & 'Yellow Jacket Fundraising 25-26'!$B$2:$B$112, 'Yellow Jacket Fundraising 25-26'!$G$2:$G$112, "Not Found")} -> Not Found | N49: N/A | O49: =vlookup(B49,'SF Roster'!A:G,7,false) -> #N/A
A50: 2095090 | B50: 003VX00000YYI6zYAH | C50: Isaiah | D50: Dowdell | E50: Isaiah Dowdell | F50: Yellow Jacket | G50: Committee Member | H50: TRUE | I50: Peter the Anteater | J50: (808) 225-3378 | K50: Isaiah.dowdell@assuredpartners.com | L50: Sales Executive Commercial Lines - Assured Partners | M50: {=XLOOKUP(C50&D50, 'Yellow Jacket Fundraising 25-26'!$A$2:$A$112 & 'Yellow Jacket Fundraising 25-26'!$B$2:$B$112, 'Yellow Jacket Fundraising 25-26'!$G$2:$G$112, "Not Found")} -> 18397 | N50: 2025-26 | O50: =vlookup(B50,'SF Roster'!A:G,7,false) -> Committee Member
A51: 2045323 | B51: 0035d0000792jwOAAQ | C51: DJ | D51: Downs | E51: DJ Downs | F51: Yellow Jacket | G51: Committee Member | H51: TRUE | I51: Dirtbags | J51: (575) 430-1850 | K51: djdowns1@gmail.com | L51: Barrett-Jackson - Sr. Director of Marketing | M51: {=XLOOKUP(C51&D51, 'Yellow Jacket Fundraising 25-26'!$A$2:$A$112 & 'Yellow Jacket Fundraising 25-26'!$B$2:$B$112, 'Yellow Jacket Fundraising 25-26'!$G$2:$G$112, "Not Found")} -> 90000 | N51: 2023-24 | O51: =vlookup(B51,'SF Roster'!A:G,7,false) -> Committee Member
A52: 105002 | C52: Jon | D52: Drago | E52: Jon Drago | F52: Yellow Jacket | H52: FALSE | J52: N/A | K52: N/A | L52: N/A | M52: {=XLOOKUP(C52&D52, 'Yellow Jacket Fundraising 25-26'!$A$2:$A$112 & 'Yellow Jacket Fundraising 25-26'!$B$2:$B$112, 'Yellow Jacket Fundraising 25-26'!$G$2:$G$112, "Not Found")} -> Not Found | N52: N/A | O52: =vlookup(B52,'SF Roster'!A:G,7,false) -> #N/A
A53: 2065267 | C53: Rob | D53: Drake | E53: Rob Drake | F53: Life Directors & Members | G53: Life Member | H53: TRUE | J53: N/A | K53: N/A | L53: N/A | M53: {=XLOOKUP(C53&D53, 'Yellow Jacket Fundraising 25-26'!$A$2:$A$112 & 'Yellow Jacket Fundraising 25-26'!$B$2:$B$112, 'Yellow Jacket Fundraising 25-26'!$G$2:$G$112, "Not Found")} -> Not Found | N53: N/A | O53: =vlookup(B53,'SF Roster'!A:G,7,false) -> #N/A
A54: 2095181 | C54: Peter | D54: Eberle | E54: Peter Eberle | F54: Life Directors & Members | G54: Life Member | H54: TRUE | J54: N/A | K54: N/A | L54: N/A | M54: {=XLOOKUP(C54&D54, 'Yellow Jacket Fundraising 25-26'!$A$2:$A$112 & 'Yellow Jacket Fundraising 25-26'!$B$2:$B$112, 'Yellow Jacket Fundraising 25-26'!$G$2:$G$112, "Not Found")} -> Not Found | N54: N/A | O54: =vlookup(B54,'SF Roster'!A:G,7,false) -> #N/A
A55: 2095190 | C55: Ed | D55: Erhardt | E55: Ed Erhardt | F55: Board of Directors | G55: Board | H55: TRUE | J55: N/A | K55: N/A | L55: N/A | M55: {=XLOOKUP(C55&D55, 'Yellow Jacket Fundraising 25-26'!$A$2:$A$112 & 'Yellow Jacket Fundraising 25-26'!$B$2:$B$112, 'Yellow Jacket Fundraising 25-26'!$G$2:$G$112, "Not Found")} -> Not Found | N55: N/A | O55: =vlookup(B55,'SF Roster'!A:G,7,false) -> #N/A
A56: 2062815 | B56: 003VX00000CeQWLYA3 | C56: Vince | D56: Ewing | E56: Vince Ewing | F56: Yellow Jacket | G56: Committee Member | H56: TRUE | I56: Fightin' Artichokes | J56: (206) 406-2162 | K56: vince@hypeathletenetwork.com | L56: Hype Athlete Network - Founder/CEO | M56: {=XLOOKUP(C56&D56, 'Yellow Jacket Fundraising 25-26'!$A$2:$A$112 & 'Yellow Jacket Fundraising 25-26'!$B$2:$B$112, 'Yellow Jacket Fundraising 25-26'!$G$2:$G$112, "Not Found")} -> $ - | N56: 2024-25 | O56: =vlookup(B56,'SF Roster'!A:G,7,false) -> Committee Member
A57: 2095198 | C57: Mark | D57: Fast | E57: Mark Fast | F57: Board of Directors | G57: Board | H57: TRUE | J57: N/A | K57: N/A | L57: N/A | M57: {=XLOOKUP(C57&D57, 'Yellow Jacket Fundraising 25-26'!$A$2:$A$112 & 'Yellow Jacket Fundraising 25-26'!$B$2:$B$112, 'Yellow Jacket Fundraising 25-26'!$G$2:$G$112, "Not Found")} -> Not Found | N57: N/A | O57: =vlookup(B57,'SF Roster'!A:G,7,false) -> #N/A
A58: 2138134 | C58: Patrick | D58: Fate | E58: Patrick Fate | F58: Yellow Jacket | G58: Future | H58: TRUE | I58: Gorlocks | J58: (602) 376-8996 | K58: pfate@devenneygroup.com | L58: Devenney Architects - Executive Director | M58: {=XLOOKUP(C58&D58, 'Yellow Jacket Fundraising 25-26'!$A$2:$A$112 & 'Yellow Jacket Fundraising 25-26'!$B$2:$B$112, 'Yellow Jacket Fundraising 25-26'!$G$2:$G$112, "Not Found")} -> Future | N58: 2026-27 | O58: =vlookup(B58,'SF Roster'!A:G,7,false) -> #N/A
A59: 2095196 | C59: Judy | D59: Ferreira | E59: Judy Ferreira | F59: Board of Directors | G59: Board | H59: TRUE | J59: N/A | K59: N/A | L59: N/A | M59: {=XLOOKUP(C59&D59, 'Yellow Jacket Fundraising 25-26'!$A$2:$A$112 & 'Yellow Jacket Fundraising 25-26'!$B$2:$B$112, 'Yellow Jacket Fundraising 25-26'!$G$2:$G$112, "Not Found")} -> Not Found | N59: N/A | O59: =vlookup(B59,'SF Roster'!A:G,7,false) -> #N/A
A60: 2041807 | B60: 0035d00006iGLZ3AAO | C60: Adam | D60: Fielding | E60: Adam Fielding | F60: Yellow Jacket | G60: Committee Member | H60: TRUE | I60: Pistol Petes | J60: (256) 861-0850 | K60: afielding821@gmail.com | L60: Platinum Dermatology Partners - Chief Compliance Officer | M60: {=XLOOKUP(C60&D60, 'Yellow Jacket Fundraising 25-26'!$A$2:$A$112 & 'Yellow Jacket Fundraising 25-26'!$B$2:$B$112, 'Yellow Jacket Fundraising 25-26'!$G$2:$G$112, "Not Found")} -> 22999 | N60: 2022-23 | O60: =vlookup(B60,'SF Roster'!A:G,7,false) -> Committee Member
A61: 2095187 | C61: Dan | D61: Filby | E61: Dan Filby | F61: Board of Directors | G61: Board | H61: TRUE | J61: N/A | K61: N/A | L61: N/A | M61: {=XLOOKUP(C61&D61, 'Yellow Jacket Fundraising 25-26'!$A$2:$A$112 & 'Yellow Jacket Fundraising 25-26'!$B$2:$B$112, 'Yellow Jacket Fundraising 25-26'!$G$2:$G$112, "Not Found")} -> Not Found | N61: N/A | O61: =vlookup(B61,'SF Roster'!A:G,7,false) -> #N/A
A62: 2041798 | B62: 0031Y00004viF9NQAU | C62: Kirk | D62: Fonfara | E62: Kirk Fonfara | F62: Yellow Jacket | G62: Committee Member | H62: TRUE | I62: Banana Slugs | J62: 602-615-9225 | K62: kirkfonfara@gmail.com | L62: Chicago Title Agency Arizona - Commercial Sales Executive | M62: {=XLOOKUP(C62&D62, 'Yellow Jacket Fundraising 25-26'!$A$2:$A$112 & 'Yellow Jacket Fundraising 25-26'!$B$2:$B$112, 'Yellow Jacket Fundraising 25-26'!$G$2:$G$112, "Not Found")} -> 96550 | N62: 2018-19 | O62: =vlookup(B62,'SF Roster'!A:G,7,false) -> Committee Member
A63: 2022970 | B63: 003VX00000CetJqYAJ | C63: Michael | D63: Fossum | E63: Michael Fossum | F63: Yellow Jacket | G63: Committee Member | H63: TRUE | I63: Speedy the Geoduck | J63: (602) 370-1097 | K63: mfossum@nobilityrcm.com | L63: NobilityRCM Founder/CEO | M63: {=XLOOKUP(C63&D63, 'Yellow Jacket Fundraising 25-26'!$A$2:$A$112 & 'Yellow Jacket Fundraising 25-26'!$B$2:$B$112, 'Yellow Jacket Fundraising 25-26'!$G$2:$G$112, "Not Found")} -> 10270 | N63: 2024-25 | O63: =vlookup(B63,'SF Roster'!A:G,7,false) -> Committee Member
A64: 2095197 | C64: Marchelle | D64: Franklin | E64: Marchelle Franklin | F64: Board of Directors | G64: Board | H64: TRUE | J64: N/A | K64: N/A | L64: N/A | M64: {=XLOOKUP(C64&D64, 'Yellow Jacket Fundraising 25-26'!$A$2:$A$112 & 'Yellow Jacket Fundraising 25-26'!$B$2:$B$112, 'Yellow Jacket Fundraising 25-26'!$G$2:$G$112, "Not Found")} -> Not Found | N64: N/A | O64: =vlookup(B64,'SF Roster'!A:G,7,false) -> #N/A
A65: 2044796 | C65: Marloshawn | D65: Franklin Jr. | E65: Marloshawn Franklin Jr. | F65: Yellow Jacket | H65: FALSE | J65: N/A | K65: N/A | L65: N/A | M65: {=XLOOKUP(C65&D65, 'Yellow Jacket Fundraising 25-26'!$A$2:$A$112 & 'Yellow Jacket Fundraising 25-26'!$B$2:$B$112, 'Yellow Jacket Fundraising 25-26'!$G$2:$G$112, "Not Found")} -> Not Found | N65: N/A | O65: =vlookup(B65,'SF Roster'!A:G,7,false) -> #N/A
A66: 2095175 | C66: William | D66: Frazier | E66: William Frazier | F66: Yellow Jacket | H66: FALSE | J66: N/A | K66: N/A | L66: N/A | M66: {=XLOOKUP(C66&D66, 'Yellow Jacket Fundraising 25-26'!$A$2:$A$112 & 'Yellow Jacket Fundraising 25-26'!$B$2:$B$112, 'Yellow Jacket Fundraising 25-26'!$G$2:$G$112, "Not Found")} -> Not Found | N66: N/A | O66: =vlookup(B66,'SF Roster'!A:G,7,false) -> #N/A
A67: 2041776 | B67: 0031Y0000637k1YQAQ | C67: Ben | D67: Fredlake | E67: Ben Fredlake | F67: Yellow Jacket | G67: Committee Member | H67: TRUE | I67: Banana Slugs | J67: (480) 323-0176 | K67: ben.fredlake@gmail.com | L67: Mission Management & Trust - Senior Portfolio Manager | M67: {=XLOOKUP(C67&D67, 'Yellow Jacket Fundraising 25-26'!$A$2:$A$112 & 'Yellow Jacket Fundraising 25-26'!$B$2:$B$112, 'Yellow Jacket Fundraising 25-26'!$G$2:$G$112, "Not Found")} -> 9641 | N67: 2021-22 | O67: =vlookup(B67,'SF Roster'!A:G,7,false) -> Committee Member
A68: 2095091 | B68: 003VX00000YtOqvYAF | C68: Ethan | D68: Freedman | E68: Ethan Freedman | F68: Yellow Jacket | G68: Committee Member | H68: TRUE | I68: Fightin' Artichokes | J68: (480) 250-8341 | K68: freedmanethan@gmail.com | L68: Burt Feldman & Grenier/Attorney | M68: {=XLOOKUP(C68&D68, 'Yellow Jacket Fundraising 25-26'!$A$2:$A$112 & 'Yellow Jacket Fundraising 25-26'!$B$2:$B$112, 'Yellow Jacket Fundraising 25-26'!$G$2:$G$112, "Not Found")} -> 9480 | N68: 2025-26 | O68: =vlookup(B68,'SF Roster'!A:G,7,false) -> Committee Member
A69: 100597 | C69: Adam | D69: Fullerton | E69: Adam Fullerton | F69: Life Directors & Members | G69: Life Member | H69: TRUE | J69: N/A | K69: N/A | L69: N/A | M69: {=XLOOKUP(C69&D69, 'Yellow Jacket Fundraising 25-26'!$A$2:$A$112 & 'Yellow Jacket Fundraising 25-26'!$B$2:$B$112, 'Yellow Jacket Fundraising 25-26'!$G$2:$G$112, "Not Found")} -> Not Found | N69: N/A | O69: =vlookup(B69,'SF Roster'!A:G,7,false) -> #N/A
A70: 97466 | C70: Jeff | D70: Gallego | E70: Jeff Gallego | F70: Yellow Jacket | H70: FALSE | J70: N/A | K70: N/A | L70: N/A | M70: {=XLOOKUP(C70&D70, 'Yellow Jacket Fundraising 25-26'!$A$2:$A$112 & 'Yellow Jacket Fundraising 25-26'!$B$2:$B$112, 'Yellow Jacket Fundraising 25-26'!$G$2:$G$112, "Not Found")} -> Not Found | N70: N/A | O70: =vlookup(B70,'SF Roster'!A:G,7,false) -> #N/A
A71: 2041841 | B71: 0035d00006iGLZ4AAO | C71: Brian | D71: Garcia-Larson | E71: Brian Garcia-Larson | F71: Yellow Jacket | G71: Committee Member | H71: TRUE | I71: Stormy Petrels | J71: 602-509-2122 | K71: bgl@bglfinancialfreedom.com | L71: Self Life Insurance Agent/Business Guide | M71: {=XLOOKUP(C71&D71, 'Yellow Jacket Fundraising 25-26'!$A$2:$A$112 & 'Yellow Jacket Fundraising 25-26'!$B$2:$B$112, 'Yellow Jacket Fundraising 25-26'!$G$2:$G$112, "Not Found")} -> 9633 | N71: 2022-23 | O71: =vlookup(B71,'SF Roster'!A:G,7,false) -> Committee Member
A72: 2041808 | C72: Harry | D72: Garewal | E72: Harry Garewal | F72: Board of Directors | G72: Board | H72: TRUE | J72: N/A | K72: N/A | L72: N/A | M72: {=XLOOKUP(C72&D72, 'Yellow Jacket Fundraising 25-26'!$A$2:$A$112 & 'Yellow Jacket Fundraising 25-26'!$B$2:$B$112, 'Yellow Jacket Fundraising 25-26'!$G$2:$G$112, "Not Found")} -> Not Found | N72: N/A | O72: =vlookup(B72,'SF Roster'!A:G,7,false) -> #N/A
A73: 100219 | C73: Dean | D73: Gekas | E73: Dean Gekas | F73: Yellow Jacket | H73: FALSE | J73: N/A | K73: N/A | L73: N/A | M73: {=XLOOKUP(C73&D73, 'Yellow Jacket Fundraising 25-26'!$A$2:$A$112 & 'Yellow Jacket Fundraising 25-26'!$B$2:$B$112, 'Yellow Jacket Fundraising 25-26'!$G$2:$G$112, "Not Found")} -> Not Found | N73: N/A | O73: =vlookup(B73,'SF Roster'!A:G,7,false) -> #N/A
A74: 2138135 | C74: Aaron | D74: Glaspie | E74: Aaron Glaspie | F74: Yellow Jacket | G74: Future | H74: TRUE | I74: Banana Slugs | J74: (313) 207-6830 | K74: aaronglaspie@yahoo.com | L74: Alkermes's Buitech /Territory Business Manager | M74: {=XLOOKUP(C74&D74, 'Yellow Jacket Fundraising 25-26'!$A$2:$A$112 & 'Yellow Jacket Fundraising 25-26'!$B$2:$B$112, 'Yellow Jacket Fundraising 25-26'!$G$2:$G$112, "Not Found")} -> Future | N74: 2026-27 | O74: =vlookup(B74,'SF Roster'!A:G,7,false) -> #N/A
A75: 100556 | C75: Chelsey | D75: Golightly | E75: Chelsey Golightly | F75: Life Directors & Members | G75: Life Member | H75: TRUE | J75: N/A | K75: N/A | L75: N/A | M75: {=XLOOKUP(C75&D75, 'Yellow Jacket Fundraising 25-26'!$A$2:$A$112 & 'Yellow Jacket Fundraising 25-26'!$B$2:$B$112, 'Yellow Jacket Fundraising 25-26'!$G$2:$G$112, "Not Found")} -> Not Found | N75: N/A | O75: =vlookup(B75,'SF Roster'!A:G,7,false) -> #N/A
A76: 2041829 | C76: Jeff | D76: Golner | E76: Jeff Golner | F76: Life Directors & Members | G76: Life Member | H76: TRUE | J76: N/A | K76: N/A | L76: N/A | M76: {=XLOOKUP(C76&D76, 'Yellow Jacket Fundraising 25-26'!$A$2:$A$112 & 'Yellow Jacket Fundraising 25-26'!$B$2:$B$112, 'Yellow Jacket Fundraising 25-26'!$G$2:$G$112, "Not Found")} -> Not Found | N76: N/A | O76: =vlookup(B76,'SF Roster'!A:G,7,false) -> #N/A
A77: 2041777 | C77: Chris | D77: Gracey | E77: Chris Gracey | F77: Life Directors & Members | G77: Life Member | H77: TRUE | J77: N/A | K77: N/A | L77: N/A | M77: {=XLOOKUP(C77&D77, 'Yellow Jacket Fundraising 25-26'!$A$2:$A$112 & 'Yellow Jacket Fundraising 25-26'!$B$2:$B$112, 'Yellow Jacket Fundraising 25-26'!$G$2:$G$112, "Not Found")} -> Not Found | N77: N/A | O77: =vlookup(B77,'SF Roster'!A:G,7,false) -> #N/A
A78: 2041809 | B78: 003i000000HAUesAAH | C78: Darius | D78: Green | E78: Darius Green | F78: Yellow Jacket | G78: Committee Member | H78: TRUE | I78: Dirtbags | J78: 602-451-5073 | K78: dgreen@keyser.com | L78: KEYSER Co-Founder & Partner | M78: {=XLOOKUP(C78&D78, 'Yellow Jacket Fundraising 25-26'!$A$2:$A$112 & 'Yellow Jacket Fundraising 25-26'!$B$2:$B$112, 'Yellow Jacket Fundraising 25-26'!$G$2:$G$112, "Not Found")} -> 9215 | N78: 40483 | O78: =vlookup(B78,'SF Roster'!A:G,7,false) -> Committee Member
A79: 2041804 | B79: 0031Y00005UIjF9QAL | C79: Brian | D79: Gubernick | E79: Brian Gubernick | F79: Yellow Jacket | G79: Committee Member | H79: TRUE | I79: Cobbers | J79: (480) 203-7928 | K79: brian@metrixtraining.com | L79: PLACE-Chief Real Estate Officer | M79: {=XLOOKUP(C79&D79, 'Yellow Jacket Fundraising 25-26'!$A$2:$A$112 & 'Yellow Jacket Fundraising 25-26'!$B$2:$B$112, 'Yellow Jacket Fundraising 25-26'!$G$2:$G$112, "Not Found")} -> 19225 | N79: 2019-20 | O79: =vlookup(B79,'SF Roster'!A:G,7,false) -> Committee Member
A80: 2062816 | B80: 003VX00000CeHstYAF | C80: Stephen | D80: Gubernick | E80: Stephen Gubernick | F80: Yellow Jacket | G80: Committee Member | H80: TRUE | I80: Pistol Petes | J80: (602) 821-9462 | K80: sgube30@yahoo.com | L80: Chiro 360-Owner | M80: {=XLOOKUP(C80&D80, 'Yellow Jacket Fundraising 25-26'!$A$2:$A$112 & 'Yellow Jacket Fundraising 25-26'!$B$2:$B$112, 'Yellow Jacket Fundraising 25-26'!$G$2:$G$112, "Not Found")} -> 2920 | N80: 2024-25 | O80: =vlookup(B80,'SF Roster'!A:G,7,false) -> Committee Member
A81: 2095092 | B81: 0035d00006RFxaKAAT | C81: Josh | D81: Guinn | E81: Josh Guinn | F81: Yellow Jacket | G81: Committee Member | H81: TRUE | I81: Dirtbags | J81: (602) 320-9337 | K81: Jguinn@eidebailly.com | L81: Eide Bailly- Director of Business Development | M81: {=XLOOKUP(C81&D81, 'Yellow Jacket Fundraising 25-26'!$A$2:$A$112 & 'Yellow Jacket Fundraising 25-26'!$B$2:$B$112, 'Yellow Jacket Fundraising 25-26'!$G$2:$G$112, "Not Found")} -> 36085 | N81: 2025-26 | O81: =vlookup(B81,'SF Roster'!A:G,7,false) -> Committee Member
A82: 104426 | C82: Brett | D82: Hansen | E82: Brett Hansen | F82: Life Directors & Members | G82: Life Member | H82: TRUE | J82: N/A | K82: N/A | L82: N/A | M82: {=XLOOKUP(C82&D82, 'Yellow Jacket Fundraising 25-26'!$A$2:$A$112 & 'Yellow Jacket Fundraising 25-26'!$B$2:$B$112, 'Yellow Jacket Fundraising 25-26'!$G$2:$G$112, "Not Found")} -> Not Found | N82: N/A | O82: =vlookup(B82,'SF Roster'!A:G,7,false) -> #N/A
A83: 87537 | B83: 0031Y00005GT8G1QAL | C83: Kirk | D83: Harbaugh | E83: Kirk Harbaugh | F83: Yellow Jacket | G83: Committee Member | H83: TRUE | I83: Gorlocks | J83: 856-366-5713 | K83: k.o.harbaugh@gmail.com | L83: Bausch + Lomb-Territory Sales Manager | M83: {=XLOOKUP(C83&D83, 'Yellow Jacket Fundraising 25-26'!$A$2:$A$112 & 'Yellow Jacket Fundraising 25-26'!$B$2:$B$112, 'Yellow Jacket Fundraising 25-26'!$G$2:$G$112, "Not Found")} -> 17566 | N83: 2019-20 | O83: =vlookup(B83,'SF Roster'!A:G,7,false) -> Committee Member
A84: 2045566 | C84: Scott | D84: Harkey | E84: Scott Harkey | F84: Life Directors & Members | G84: Life Member | H84: TRUE | J84: N/A | K84: N/A | L84: N/A | M84: {=XLOOKUP(C84&D84, 'Yellow Jacket Fundraising 25-26'!$A$2:$A$112 & 'Yellow Jacket Fundraising 25-26'!$B$2:$B$112, 'Yellow Jacket Fundraising 25-26'!$G$2:$G$112, "Not Found")} -> Not Found | N84: N/A | O84: =vlookup(B84,'SF Roster'!A:G,7,false) -> #N/A
A85: 2095212 | C85: Bob | D85: Hart | E85: Bob Hart | F85: Life Directors & Members | G85: Life Member | H85: TRUE | J85: N/A | K85: N/A | L85: N/A | M85: {=XLOOKUP(C85&D85, 'Yellow Jacket Fundraising 25-26'!$A$2:$A$112 & 'Yellow Jacket Fundraising 25-26'!$B$2:$B$112, 'Yellow Jacket Fundraising 25-26'!$G$2:$G$112, "Not Found")} -> Not Found | N85: N/A | O85: =vlookup(B85,'SF Roster'!A:G,7,false) -> #N/A
A86: 2044797 | B86: 0035d0000793mJEAAY | C86: Gabriel | D86: Hartsell | E86: Gabriel Hartsell | F86: Yellow Jacket | G86: Committee Member | H86: TRUE | I86: Fighting Pickles | J86: (239) 560-7778 | K86: hartsell.gabriel@dorsey.com | L86: Dorsey & Whitney-Attorney/Partner | M86: {=XLOOKUP(C86&D86, 'Yellow Jacket Fundraising 25-26'!$A$2:$A$112 & 'Yellow Jacket Fundraising 25-26'!$B$2:$B$112, 'Yellow Jacket Fundraising 25-26'!$G$2:$G$112, "Not Found")} -> 35519 | N86: 2023-24 | O86: =vlookup(B86,'SF Roster'!A:G,7,false) -> Committee Member
A87: 2044798 | B87: 0035d0000793m3BAAQ | C87: Amy | D87: Harvath | E87: Amy Harvath | F87: Yellow Jacket | G87: Committee Member | H87: TRUE | I87: Fightin' Artichokes | J87: (586) 350-8668 | K87: a.harvath@greenlinkhcm.com | L87: Greenlink HCM-VP of Business Development | M87: {=XLOOKUP(C87&D87, 'Yellow Jacket Fundraising 25-26'!$A$2:$A$112 & 'Yellow Jacket Fundraising 25-26'!$B$2:$B$112, 'Yellow Jacket Fundraising 25-26'!$G$2:$G$112, "Not Found")} -> 14040 | N87: 2023-24 | O87: =vlookup(B87,'SF Roster'!A:G,7,false) -> Committee Member
A88: 2041796 | C88: Ryan | D88: Hatch | E88: Ryan Hatch | F88: Board of Directors | G88: Board | H88: TRUE | J88: N/A | K88: N/A | L88: N/A | M88: {=XLOOKUP(C88&D88, 'Yellow Jacket Fundraising 25-26'!$A$2:$A$112 & 'Yellow Jacket Fundraising 25-26'!$B$2:$B$112, 'Yellow Jacket Fundraising 25-26'!$G$2:$G$112, "Not Found")} -> Not Found | N88: N/A | O88: =vlookup(B88,'SF Roster'!A:G,7,false) -> #N/A
A89: 2041810 | C89: Jim | D89: Hatfield | E89: Jim Hatfield | F89: Life Directors & Members | G89: Life Director | H89: TRUE | J89: N/A | K89: N/A | L89: N/A | M89: {=XLOOKUP(C89&D89, 'Yellow Jacket Fundraising 25-26'!$A$2:$A$112 & 'Yellow Jacket Fundraising 25-26'!$B$2:$B$112, 'Yellow Jacket Fundraising 25-26'!$G$2:$G$112, "Not Found")} -> Not Found | N89: N/A | O89: =vlookup(B89,'SF Roster'!A:G,7,false) -> #N/A
A90: 103208 | C90: Brandon | D90: Hebert | E90: Brandon Hebert | F90: Yellow Jacket | H90: FALSE | J90: N/A | K90: N/A | L90: N/A | M90: {=XLOOKUP(C90&D90, 'Yellow Jacket Fundraising 25-26'!$A$2:$A$112 & 'Yellow Jacket Fundraising 25-26'!$B$2:$B$112, 'Yellow Jacket Fundraising 25-26'!$G$2:$G$112, "Not Found")} -> Not Found | N90: N/A | O90: =vlookup(B90,'SF Roster'!A:G,7,false) -> #N/A
A91: 2041778 | B91: 0035d00006iGLazAAG | C91: Renee | D91: Higgs | E91: Renee Higgs | F91: Yellow Jacket | G91: Committee Member | H91: TRUE | I91: Speedy the Geoduck | J91: 425-802-8844 | K91: reneejhiggs@gmail.com | L91: Salt River Project (SRP) - Sr. Marketing Strategist | M91: {=XLOOKUP(C91&D91, 'Yellow Jacket Fundraising 25-26'!$A$2:$A$112 & 'Yellow Jacket Fundraising 25-26'!$B$2:$B$112, 'Yellow Jacket Fundraising 25-26'!$G$2:$G$112, "Not Found")} -> 132413 | N91: 2022-23 | O91: =vlookup(B91,'SF Roster'!A:G,7,false) -> Committee Member
A92: 2095176 | C92: Troy | D92: Hoberg | E92: Troy Hoberg | F92: Yellow Jacket | H92: FALSE | J92: N/A | K92: N/A | L92: N/A | M92: {=XLOOKUP(C92&D92, 'Yellow Jacket Fundraising 25-26'!$A$2:$A$112 & 'Yellow Jacket Fundraising 25-26'!$B$2:$B$112, 'Yellow Jacket Fundraising 25-26'!$G$2:$G$112, "Not Found")} -> Not Found | N92: N/A | O92: =vlookup(B92,'SF Roster'!A:G,7,false) -> #N/A
A93: 2041856 | C93: Randall | D93: Hoggard | E93: Randall Hoggard | F93: Yellow Jacket | H93: FALSE | J93: N/A | K93: N/A | L93: N/A | M93: {=XLOOKUP(C93&D93, 'Yellow Jacket Fundraising 25-26'!$A$2:$A$112 & 'Yellow Jacket Fundraising 25-26'!$B$2:$B$112, 'Yellow Jacket Fundraising 25-26'!$G$2:$G$112, "Not Found")} -> Not Found | N93: N/A | O93: =vlookup(B93,'SF Roster'!A:G,7,false) -> #N/A
A94: 2041850 | B94: 003i000000HAUe2AAH | C94: Joe | D94: Hourigan | E94: Joe Hourigan | F94: Yellow Jacket | G94: Committee Member | H94: TRUE | I94: Cobbers | J94: 518-588-6883 | K94: hourigan.joseph@gmail.com | L94: Petti and Briones - Attorney | M94: {=XLOOKUP(C94&D94, 'Yellow Jacket Fundraising 25-26'!$A$2:$A$112 & 'Yellow Jacket Fundraising 25-26'!$B$2:$B$112, 'Yellow Jacket Fundraising 25-26'!$G$2:$G$112, "Not Found")} -> 10063 | N94: 40878 | O94: =vlookup(B94,'SF Roster'!A:G,7,false) -> Committee Member
A95: 2041843 | C95: Randle | D95: House | E95: Randle House | F95: Board of Directors | G95: Board | H95: TRUE | J95: N/A | K95: N/A | L95: N/A | M95: {=XLOOKUP(C95&D95, 'Yellow Jacket Fundraising 25-26'!$A$2:$A$112 & 'Yellow Jacket Fundraising 25-26'!$B$2:$B$112, 'Yellow Jacket Fundraising 25-26'!$G$2:$G$112, "Not Found")} -> Not Found | N95: N/A | O95: =vlookup(B95,'SF Roster'!A:G,7,false) -> #N/A
A96: 2044799 | B96: 0035d0000793oB0AAI | C96: Karen | D96: Howard | E96: Karen Howard | F96: Yellow Jacket | G96: Committee Member | H96: TRUE | I96: Blue Hose | J96: (480) 213-3306 | K96: howard@hotmail.com | L96: ka , , Land Resources - Real Estate Development (Vice President) | M96: {=XLOOKUP(C96&D96, 'Yellow Jacket Fundraising 25-26'!$A$2:$A$112 & 'Yellow Jacket Fundraising 25-26'!$B$2:$B$112, 'Yellow Jacket Fundraising 25-26'!$G$2:$G$112, "Not Found")} -> 9739 | N96: 2023-24 | O96: =vlookup(B96,'SF Roster'!A:G,7,false) -> Committee Member
A97: 2044800 | C97: Justin | D97: Humpal | E97: Justin Humpal | F97: Yellow Jacket | H97: FALSE | J97: N/A | K97: N/A | L97: N/A | M97: {=XLOOKUP(C97&D97, 'Yellow Jacket Fundraising 25-26'!$A$2:$A$112 & 'Yellow Jacket Fundraising 25-26'!$B$2:$B$112, 'Yellow Jacket Fundraising 25-26'!$G$2:$G$112, "Not Found")} -> Not Found | N97: N/A | O97: =vlookup(B97,'SF Roster'!A:G,7,false) -> #N/A
A98: 2044801 | B98: 0035d0000793mOmAAI | C98: Chad | D98: Hunter | E98: Chad Hunter | F98: Yellow Jacket | G98: Committee Member | H98: TRUE | I98: Speedy the Geoduck | J98: (623) 824-9788 | K98: chad.hunter@bmo.com | L98: BMO Financial Group - Director Commercial Bank | M98: {=XLOOKUP(C98&D98, 'Yellow Jacket Fundraising 25-26'!$A$2:$A$112 & 'Yellow Jacket Fundraising 25-26'!$B$2:$B$112, 'Yellow Jacket Fundraising 25-26'!$G$2:$G$112, "Not Found")} -> 86889 | N98: 2023-24 | O98: =vlookup(B98,'SF Roster'!A:G,7,false) -> Committee Member
A99: 2095093 | B99: 003VX00000Z9EXRYA3 | C99: Michael | D99: Jackson | E99: Michael Jackson | F99: Yellow Jacket | G99: Committee Member | H99: TRUE | I99: Stormy Petrels | J99: (719) 201-2462 | K99: mjackson@myakal.com | L99: CEO-Mya Kal | M99: {=XLOOKUP(C99&D99, 'Yellow Jacket Fundraising 25-26'!$A$2:$A$112 & 'Yellow Jacket Fundraising 25-26'!$B$2:$B$112, 'Yellow Jacket Fundraising 25-26'!$G$2:$G$112, "Not Found")} -> 14775 | N99: 2025-26 | O99: =vlookup(B99,'SF Roster'!A:G,7,false) -> Committee Member
A100: 2041824 | C100: Chet | D100: Jaehnig | E100: Chet Jaehnig | F100: Life Directors & Members | G100: Life Member | H100: TRUE | J100: N/A | K100: N/A | L100: N/A | M100: {=XLOOKUP(C100&D100, 'Yellow Jacket Fundraising 25-26'!$A$2:$A$112 & 'Yellow Jacket Fundraising 25-26'!$B$2:$B$112, 'Yellow Jacket Fundraising 25-26'!$G$2:$G$112, "Not Found")} -> Not Found | N100: N/A | O100: =vlookup(B100,'SF Roster'!A:G,7,false) -> #N/A
...

Sheet SF Roster
A1: Full Contact ID | C1: First Name | D1: Last Name | E1: Yellow Jacket Team | F1: First Year of Volunteering | G1: Bowl Position
A2: 0031Y0000637jKFQAY | C2: Bob | D2: Aggarwal | E2: Fighting Pickles | F2: 2021 | G2: Committee Member
A3: 0031Y0000637jiWQAQ | C3: Jonathan | D3: Amato | E3: Blue Hose | F3: 2020 | G3: Committee Member
A4: 0035d00006NTQsiAAH | C4: Jeffrey | D4: Anderson | E4: Speedy the Geoduck | F4: 2021 | G4: Committee Member
A5: 003i000000HAUd8AAH | C5: Eric | D5: Barkyoumb | E5: Pistol Petes | F5: 2012 | G5: Committee Member
A6: 0035d00006iGLA8AAO | C6: Warren | D6: Black | E6: Peter the Anteater | F6: 2022 | G6: Committee Member
A7: 0035d0000793oC6AAI | C7: Bryan | D7: Boyer | E7: Fighting Pickles | F7: 2023 | G7: Committee Member
A8: 0035d00006iGLX7AAO | C8: Justin | D8: Bretag | E8: Peter the Anteater | F8: 2022 | G8: Committee Member
A9: 0035d0000793o4ZAAQ | C9: Lindsey | D9: Brist | E9: Gorlocks | F9: 2023 | G9: Committee Member
A10: 0031Y00005kTGeIQAW | C10: Taylor | D10: Burgoon | E10: Blue Hose | F10: 2019 | G10: Committee Member
A11: 0035d00006iGLXqAAO | C11: Benjamin | D11: Burke | E11: Blue Hose | F11: 2022 | G11: Committee Member
A12: 003VX00000CeOJGYA3 | C12: Ben | D12: Calacci | E12: Speedy the Geoduck | F12: 2024 | G12: Committee Member
... A52: 003i000002KdHH1AAN | C52: Kirk | D52: McClure | E52: Fighting Camels | F52: 2016 | G52: Committee Member
A53: 003VX00000voHuUYAU | C53: Sean | D53: McEvilly | G53: Fiesta Future
A54: 0035d00006NTR74AAH | C54: Kyle | D54: McMillian | E54: Speedy the Geoduck | F54: 2021 | G54: Committee Member
A55: 003VX00000YQPKAYA5 | C55: Damien | D55: Meyer | E55: Banana Slugs | F55: 2025 | G55: Committee Member
A56: 003i000001LGx5FAAT | C56: John | D56: Meza | E56: Gorlocks | F56: 2016 | G56: Committee Member
A57: 003VX00000CfFgvYAF | C57: Tim | D57: Miller | E57: Pistol Petes | F57: 2024 | G57: Committee Member
A58: 003i000000HAUduAAH | C58: Brian | D58: Moll | E58: Speedy the Geoduck | F58: 2011 | G58: Committee Member
A59: 003VX00000voZoBYAU | C59: Rogelio | D59: Monzon | G59: Fiesta Future
A60: 0031Y00005kTGlsQAG | C60: Brad | D60: Morin | E60: Fighting Camels | F60: 2019 | G60: Committee Member
A61: 0031Y00005GT8HTQA1 | C61: Justin | D61: Naber | E61: Stormy Petrels | F61: 2018 | G61: Committee Member
A62: 0035d00006NTR7JAAX | C62: Gary | D62: Naquin | E62: Stormy Petrels | F62: 2021 | G62: Committee Member
A63: 003VX00000YjxTPYAZ | C63: Will | D63: Nation | E63: Fighting Pickles | F63: 2025 | G63: Committee Member
A64: 0035d00006viTv5AAE | C64: Suzanne | D64: Nelson | E64: Fighting Pickles | F64: 2023 | G64: Committee Member
A65: 003VX00000CfAAzYAN | C65: Jameson | D65: Neuhoff | E65: Peter the Anteater | F65: 2024 | G65: Committee Member
A66: 003i000000HAUdAAAX | C66: Tim | D66: Newquist | E66: Stormy Petrels | F66: 2012 | G66: Committee Member
A67: 003VX00000CfG9xYAF | C67: Brian | D67: Nuestro | E67: Speedy the Geoduck | F67: 2024 | G67: Committee Member
A68: 0031Y0000637kLTQAY | C68: Jerry | D68: Pence | E68: Fighting Camels | F68: 2020 | G68: Committee Member
A69: 0035d0000793lYsAAI | C69: Ryan | D69: Penniman | E69: Dirtbags | F69: 2023 | G69: Committee Member
A70: 003i000000NFnzBAAT | C70: Kelly | D70: Peru | E70: Speedy the Geoduck | F70: 2013 | G70: Committee Member
A71: 0031Y0000637kLiQAI | C71: Shane | D71: Peterlin | E71: Banana Slugs | F71: 2021 | G71: Committee Member
... A88: 0031Y0000637kNoQAI | C88: Joe | D88: Strening | E88: Fighting Camels | F88: 2020 | G88: Committee Member
A89: 003VX00000vnkbPYAQ | C89: Scot | D89: Taggart | G89: Fiesta Future
A90: 0035d0000793iTlAAI | C90: David | D90: Tatko | E90: Stormy Petrels | F90: 2023 | G90: Committee Member
A91: 0035d00006iGLZ6AAO | C91: Danny | D91: Thielen | E91: Dirtbags | F91: 2022 | G91: Committee Member
A92: 0031Y0000637kQnQAI | C92: Oye | D92: Waddell | E92: Sammy the Slug | F92: 2022 | G92: Committee Member
A93: 0031Y00005GT8MYQA1 | C93: Sean | D93: Ward | E93: Cobbers | F93: 2018 | G93: Committee Member
A94: 003i000001O9C8PAAV | C94: Josh | D94: Wein | E94: Banana Slugs | F94: 2016 | G94: Committee Member
A95: 003i000000w9NxVAAU | C95: David | D95: Weissman | E95: Dirtbags | F95: 2014 | G95: Committee Member
A96: 003i000000w9NxUAAU | C96: Andrew | D96: Western | E96: Cobbers | F96: 2014 | G96: Committee Member
A97: 003i000000NFo0DAAT | C97: Antone | D97: White | E97: Dirtbags | F97: 2018 | G97: Committee Member
A98: 0031Y00005kTGwbQAG | C98: Larry | D98: White | E98: Sammy the Slug | F98: 2019 | G98: Committee Member
A99: 003VX00000Yvt7SYAR | C99: Aaron | D99: Wiese | E99: Pistol Petes | F99: 2025 | G99: Committee Member
A100: 0035d00006iGLexAAG | C100: Rick | D100: Zieglowsky | E100: Banana Slugs | F100: 2022 | G100: Committee Member
A101: 0031Y00005kTGzuQAG | C101: Frank | D101: Zimmerman | E101: Banana Slugs | F101: 2019 | G101: Committee Member
A102: Total | B102: Count | C102: 100

Sheet Yellow Jacket Fundraising 25-26
A1: First name | B1: Last name | C1: Full Name | D1: Email | E1: Phone | F1: Job | G1: 25-26 Fundraising Dollars | H1: 25-26 Fundraising Rank | I1: Future Class
A2: Chip | B2: Pray | C2: Chip Pray | D2: charles.pray@mclanefs.com | E2: (480) 266-8583 | F2: McLane Company Inc. General Manager | G2: 261599 | H2: 2 | I2: 2022-23
A3: Tim | B3: Newquist | C3: Tim Newquist | D3: tim@newquistinvestments.com | E3: 480-577-0847 | F3: Newquist Investments - Owner/Real Estate Investor/Consultant | G3: 187484 | H3: 3 | I3: 2012-13
A4: Renee | B4: Higgs | C4: Renee Higgs | D4: reneejhiggs@gmail.com | E4: 425-802-8844 | F4: Salt River Project (SRP) - Sr. Marketing Strategist | G4: 132413 | H4: 4 | I4: 2022-23
A5: Josh | B5: Wein | C5: Josh Wein | D5: weintime@gmail.com | E5: 480-432-4771 | F5: Home Smart - Residential Real Estate Sales Professional | G5: 120306 | H5: 5 | I5: 2016-17
A6: Logan | B6: Senoski | C6: Logan Senoski | D6: Logan.Senoski@srpnet.com | E6: (505) 401-6399 | F6: Salt River Project (SRP) - Senior Project Origination Consultant | G6: 119909 | H6: 6 | I6: 2018-19
A7: Kyle | B7: McMillian | C7: Kyle McMillian | D7: kyle.mcmillian@umb.com | E7: 913-620-6577 | F7: UMB Bank-Senior VP Commercial Banking Officer | G7: 115875 | H7: 7 | I7: 2021-22
A8: Eric | B8: Barkyoumb | C8: Eric Barkyoumb | D8: ebarkyoumb@gmail.com | E8: 480-209-7993 | F8: Dignity Health Foundation - Philanthropy Manager | G8: 115548 | H8: 8 | I8: 2012-13
A9: Kirk | B9: McClure | C9: Kirk McClure | D9: kirk.mcclure@jedunn.com | E9: (480) 305-3902 | F9: JE Dunn Construction - Vice President | G9: 99540 | H9: 9 | I9: 2016-17
A10: Kirk | B10: Fonfara | C10: Kirk Fonfara | D10: kirkfonfara@gmail.com | E10: 602-615-9225 | F10: Chicago Title Agency Arizona - Commercial Sales Executive | G10: 96550 | H10: 10 | I10: 2018-19
A11: DJ | B11: Downs | C11: DJ Downs | D11: djdowns1@gmail.com | E11: (575) 430-1850 | F11: Barrett-Jackson - Sr. Director of Marketing | G11: 90000 | H11: 11 | I11: 2023-24
A12: Chad | B12: Hunter | C12: Chad Hunter | D12: chad.hunter@bmo.com | E12: (623) 824-9788 | F12: BMO Financial Group - Director Commercial Bank | G12: 86889 | H12: 12 | I12: 2023-24
A13: William | B13: Jaffe | C13: William Jaffe | D13: williamjaffe@gmail.com | E13: (520) 360-8820 | F13: Abrazo Biltmore Cardiology-Preventative Cardiologist | G13: 66195 | H13: 13 | I13: 2023-24
... A15: Melissa | B15: Stack | C15: Melissa Stack | D15: melvittone@gmail.com | E15: (815) 228-0560 | F15: Deloitte LLP-Sr. Manager Risk and Brand Protection | G15: 52104 | H15: 15 | I15: 2024-25
A16: Jonathan | B16: Levin | C16: Jonathan Levin | D16: jonathanhlevin@gmail.com | E16: 480-313-0141 | F16: Zeta Beta Tau Foundation - Vice President of Development | G16: 50378 | H16: 16 | I16: 39692
A17: Justin | B17: Bretag | C17: Justin Bretag | D17: Justin.bretag@busey.com | E17: (602) 361-7027 | F17: Busey Bank-Managing Director Commercial | G17: 50127 | H17: 17 | I17: 2022-23
A18: Rick | B18: Zieglowsky | C18: Rick Zieglowsky | D18: rick.zieglowsky@gmail.com | E18: 480-993-8707 | F18: American Arbitration Association - Vice President-Construction | G18: 46585 | H18: 18 | I18: 2022-23
A19: Jonathan | B19: Amato | C19: Jonathan Amato | D19: jonathan.amato@westin.com | E19: 914-494-3179 | F19: The Westin Kierland Resort & Spa - Director of Sales and Marketing | G19: 46431 | H19: 19 | I19: 2020-21
A20: Mike | B20: Lindsley | C20: Mike Lindsley | D20: mike@bfoxg.com | E20: 480-326-3120 | F20: BlueFox Group-Partner | G20: 42030 | H20: 20 | I20: 40878
A21: Samantha | B21: Spadaro | C21: Samantha Spadaro | D21: sspadaro113@gmail.com | E21: 2032495791 | G21: 41525 | H21: 21 | I21: 2022-23
A22: Jeffrey | B22: Anderson | C22: Jeffrey Anderson | D22: Jeff.anderson@aleragroup.com | E22: (602) 321-9660 | F22: BCG 401(k) Advisors - President | G22: 39259 | H22: 22 | I22: 2021-22
A23: Ryan | B23: Delaney | C23: Ryan Delaney | D23: ryan.delaney@busey.com | E23: 319-470-3845 | F23: Busey Bank - Senior VP Director of Middle Market Banking | G23: 38690 | H23: 23 | I23: 2020-21
A24: Tim | B24: Martin | C24: Tim Martin | D24: timmartin602@yahoo.com | E24: (602) 505-0052 | F24: Arizona Athletic Grounds - VP of Sales | G24: 37856 | H24: 25 | I24: 2023-24
A25: Josh | B25: Guinn | C25: Josh Guinn | D25: Jguinn@eidebailly.com | E25: (602) 320-9337 | F25: Eide Bailly- Director of Business Development | G25: 36085 | H25: 26 | I25: 2025-26
A26: Justin | B26: Naber | C26: Justin Naber | D26: jnaber@brixnational.com | E26: 480-487-7558 | F26: Brix Paving Northwest Inc. - VP of Business Development | G26: 36076 | H26: 27 | I26: 2018-19
A27: Gabriel | B27: Hartsell | C27: Gabriel Hartsell | D27: hartsell.gabriel@dorsey.com | E27: (239) 560-7778 | F27: Dorsey & Whitney-Attorney/Partner | G27: 35519 | H27: 28 | I27: 2023-24
A28: Richie | B28: Schmock | C28: Richie Schmock | D28: richard.schmock@gmail.com | E28: 602-402-6835 | F28: Rockefeller Capital Management- Sr. Vice President | G28: 30000 | H28: 30 | I28: 40087
A29: Andrew | B29: Western | C29: Andrew Western | D29: awestern@omiaw.com | E29: 602-329-3477 | F29: Osborn Maledon - Partner | G29: 29428 | H29: 31 | I29: 2014-15
A30: Justin | B30: Pierce | C30: Justin Pierce | D30: drjustinpierce@gmail.com | E30: (517) 214-2501 | F30: Valley Spinal Care/ Owner | G30: 29243 | H30: 32 | I30: 2025-26
A31: Lindsey | B31: Brist | C31: Lindsey Brist | D31: lindsey.brist@mmrgrp.com | E31: (208) 631-7601 | F31: MMR Constructors - Business Development Manager | G31: 27359 | H31: 33 | I31: 2023-24
A32: Brian | B32: Moll | C32: Brian Moll | D32: bkm2@cox.net | E32: (602) 741-7775 | F32: Dorsey & Whitney LLP - Partner | G32: 27020 | H32: 34 | I32: 40878
A33: Kyler | B33: Robinson | C33: Kyler Robinson | D33: krobinson@crestins.com | E33: (307) 421-9811 | F33: Crest Insurance Group Commercial Insurance Broker | G33: 24768 | H33: 35 | I33: 2024-25
A34: Adam | B34: Fielding | C34: Adam Fielding | D34: afielding821@gmail.com | E34: (256) 861-0850 | F34: Platinum Dermatology Partners - Chief Compliance Officer | G34: 22999 | H34: 36 | I34: 2022-23
A35: Kelly | B35: Peru | C35: Kelly Peru | D35: kellyperu22@gmail.com | E35: 480-330-4316 | F35: Yellow Jacket Committee Member | G35: 22922 | H35: 37 | I35: 2013-14
A36: Danny | B36: Thielen | C36: Danny Thielen | D36: daniel.m.thielen@gmail.com | E36: 602-3505881 | F36: Axon Enterprise - Strategic Account Executive | G36: 21190 | H36: 38 | I36: 2022-23
A37: David | B37: Weissman | C37: David Weissman | D37: diweissman@gmail.com | E37: 602-535-6303 | F37: Davis Miles - Partner | G37: 21112 | H37: 39 | I37: 2014-15
A38: Will | B38: Nation | C38: Will Nation | D38: wnation@mtbuilders.com | E38: (602) 980-2336 | F38: MT Builders - President | G38: 20975 | H38: 40 | I38: 2025-26
A39: Brian | B39: Debnam | C39: Brian Debnam | D39: bkdebnam@gmail.com | E39: (520) 990-7030 | F39: NIKE Inc-Director & Chief of Staff Global Footwear Product Creation | G39: 20642 | H39: 41 | I39: 2017-18
A40: Bob | B40: Aggarwal | C40: Bob Aggarwal | D40: baggarwal@alliancebankofarizona.com | E40: 480-323-0560 | F40: Alliance Bank-VP Commercial Banking | G40: 20112 | H40: 42 | I40: 2021-22
A41: Ben | B41: Calacci | C41: Ben Calacci | D41: ben.calacci@gmail.com | E41: (703) 967-7691 | F41: Team Velocity - Vice President OEM | G41: 20034 | H41: 43 | I41: 2024-25
A42: Ty | B42: Martin | C42: Ty Martin | D42: Tymartin602@yahoo.com | E42: 602-403-2390 | F42: Grand Canyon University - Sr. Director of Corporate Partnerships | G42: 19810 | H42: 44 | I42: 2018-19
A43: Frank | B43: Zimmerman | C43: Frank Zimmerman | D43: frank@rbwcompanies.com | E43: (602) 738-1103 | F43: RBW Companies/R.B. White - COO | G43: 19565 | H43: 45 | I43: 2019-20
A44: Warren | B44: Black | C44: Warren Black | D44: warren.c.black@outlook.com | E44: 480-285-8502 | F44: Merrill Lynch - Financial Advisor Senior Portfolio Advisor | G44: 19523 | H44: 46 | I44: 2022-23
... A75: Michael | B75: Fossum | C75: Michael Fossum | D75: mfossum@nobilityrcm.com | E75: (602) 370-1097 | F75: NobilityRCM Founder/CEO | G75: 10270 | H75: 78 | I75: 2024-25
A76: Joe | B76: Hourigan | C76: Joe Hourigan | D76: hourigan.joseph@gmail.com | E76: 518-588-6883 | F76: Petti and Briones - Attorney | G76: 10063 | H76: 79 | I76: 40878
A77: Karen | B77: Howard | C77: Karen Howard | D77: howard@hotmail.com | E77: (480) 213-3306 | F77: ka , , Land Resources - Real Estate Development (Vice President) | G77: 9739 | H77: 80 | I77: 2023-24
A78: Ben | B78: Fredlake | C78: Ben Fredlake | D78: ben.fredlake@gmail.com | E78: (480) 323-0176 | F78: Mission Management & Trust - Senior Portfolio Manager | G78: 9641 | H78: 81 | I78: 2021-22
A79: Brian | B79: Garcia-Larson | C79: Brian Garcia-Larson | D79: bgl@bglfinancialfreedom.com | E79: 602-509-2122 | F79: Self Life Insurance Agent/Business Guide | G79: 9633 | H79: 82 | I79: 2022-23
A80: Ethan | B80: Freedman | C80: Ethan Freedman | D80: freedmanethan@gmail.com | E80: (480) 250-8341 | F80: Burt Feldman & Grenier/Attorney | G80: 9480 | H80: 83 | I80: 2025-26
A81: Katelyn | B81: Saunders | C81: Katelyn Saunders | D81: katelyn@metrixtraining.com | E81: (480) 201-6506 | F81: Metrix Masterminds - Head of Growth and Operations | G81: 9375 | H81: 84 | I81: 2024-25
A82: Darius | B82: Green | C82: Darius Green | D82: dgreen@keyser.com | E82: 602-451-5073 | F82: KEYSER Co-Founder & Partner | G82: 9215 | H82: 85 | I82: 40483
A83: John | B83: Knebel | C83: John Knebel | D83: johnknebel3@gmail.com | E83: (202) 421-7042 | F83: Influence Sports & Media - SVP Business Development | G83: 9064 | H83: 86 | I83: 2019-20
A84: Brad | B84: Morin | C84: Brad Morin | D84: Bradley.morin@rrd.com | E84: 269-998-0675 | F84: Digital Media Consultant/R.R. Donnelly | G84: 8500 | H84: 87 | I84: 2019-20
A85: Bryan | B85: Boyer | C85: Bryan Boyer | D85: bboyer7740@gmail.com | E85: 480-267-4169 | F85: Avis/Budget Group - Business Development Manager | G85: 8493 | H85: 88 | I85: 2023-24
A86: Benjamin | B86: Burke | C86: Benjamin Burke | D86: benburke@msn.com | E86: 608-385-4078 | F86: Van Wagner-Vice President College Division | G86: 8158 | H86: 89 | I86: 2022-23
A87: Steven | B87: Kruczek | C87: Steven Kruczek | D87: kruczek@post.harvard.edu | E87: (480) 678-3506 | F87: AeroGuard Flight Training - Chief Financial Officer | G87: 7765 | H87: 90 | I87: 2015-16
A88: Steven | B88: Davis | C88: Steven Davis | D88: Steven@RdEnterprisesaz.com | E88: (602) 284-8681 | F88: RD Enterprises - Managing Partner | G88: 7711 | H88: 91 | I88: 2023-24
A89: Justin | B89: Johnson | C89: Justin Johnson | D89: doublejsales@gmail.com | E89: (480) 521-1855 | F89: Dunlop Sports Americas - Regional Sales Manager | G89: 7637 | H89: 92 | I89: 2024-25
A90: Ryan | B90: Penniman | C90: Ryan Penniman | D90: repenniman@gmail.com | E90: (480) 266-9993 | F90: CAPTRUST-Principal | Financial Advisor | G90: 7610 | H90: 93 | I90: 2023-24
A91: Greg | B91: Stark | C91: Greg Stark | D91: gkstark34@gmail.com | E91: (602) 418-6877 | F91: Raymond James - Financial Advisor CFP(R) | G91: 7575 | H91: 94 | I91: 2016-17
A92: Jared | B92: Shahon | C92: Jared Shahon | D92: jbshahon@gmail.com | E92: (602) 904-2362 | F92: Launch Powered by Compass - Realtor | G92: 7565 | H92: 95 | I92: 2024-25
A93: Max | B93: Starks | C93: Max Starks | D93: maxstarks78@me.com | E93: 352-256-7949 | F93: SiriusXM-On-Air Talent | G93: 7150 | H93: 96 | I93: 2021-22
A94: Brian | B94: Nuestro | C94: Brian Nuestro | D94: bnuestro@gmail.com | E94: (480) 689-1167 | F94: Marc & Rose Hospitality - VP of IT & Cybersecurity | G94: 4000 | H94: 100 | I94: 2024-25
... A98: Shane | B98: Peterlin | C98: Shane Peterlin | D98: shane@c21seago.com | E98: 480-227-2019 | F98: Century 21 Seago - Realtor | G98: 730 | H98: 106 | I98: 2021-22
A99: Oye | B99: Waddell | C99: Oye Waddell | D99: oye.waddell@hustlephx.com | E99: 323-972-2305 | F99: Hustle PHX - CEO | G99: $ - | H99: 107 | I99: 2022-23
A100: Vince | B100: Ewing | C100: Vince Ewing | D100: vince@hypeathletenetwork.com | E100: (206) 406-2162 | F100: Hype Athlete Network - Founder/CEO | G100: $ - | H100: 108 | I100: 2024-25
A101: Daniel | B101: Akmon | C101: Daniel Akmon | D101: Daniel.akmon@claconnect.com | E101: (602) 361-4600 | F101: CLA-Principal | G101: Future | H101: Future | I101: 2026-27
A102: Chancellor | B102: Barjona | C102: Chancellor Barjona | D102: chancellor.barjona@gmail.com | E102: (480) 599-9198 | F102: IBM Principle Data & AI Leader - Financial Services | G102: Future | H102: Future | I102: 2026-27
A103: Tyler | B103: Butler | C103: Tyler Butler | D103: connect@collaborationforgood.com | E103: (480) 431-8580 | F103: Collaboration for Good Founder | G103: Future | H103: Future | I103: 2026-27
A104: Sarah | B104: Desmond | C104: Sarah Desmond | D104: sarah.desmond@ubs.com | E104: (602) 826-8866 | F104: UBS/Financial Advisor | G104: Future | H104: Future | I104: 2026-27
A105: Patrick | B105: Fate | C105: Patrick Fate | D105: pfate@devenneygroup.com | E105: (602) 376-8996 | F105: Devenney Architects - Executive Director | G105: Future | H105: Future | I105: 2026-27
A106: Aaron | B106: Glaspie | C106: Aaron Glaspie | D106: aaronglaspie@yahoo.com | E106: (313) 207-6830 | F106: Alkermes's Buitech /Territory Business Manager | G106: Future | H106: Future | I106: 2026-27
A107: Aaron | B107: Kacer | C107: Aaron Kacer | D107: Aaron@milliganlawless.com | E107: (641) 425-8499 | F107: Milligan Lawless P.C. Lawyer | G107: Future | H107: Future | I107: 2026-27
A108: Matt | B108: Masin | C108: Matt Masin | D108: matt@xpertadvice.com | E108: (330) 209-9063 | F108: Strategic Wealth Advisors LLC Financial Advisor | G108: Future | H108: Future | I108: 2026-27
A109: Sean | B109: McEvilly | C109: Sean McEvilly | D109: smcevilly@vistamarkllc.com | E109: (714) 357-2290 | F109: Vistamark Investments/Managing Partner | G109: Future | H109: Future | I109: 2026-27
A110: Rogelio | B110: Monzon | C110: Rogelio Monzon | D110: rogelio.monzon3@gmail.com | E110: (602) 509-2301 | F110: Aspire Counseling Services / Chief Financial Officer | G110: Future | H110: Future | I110: 2026-27
A111: Tony | B111: Motta | C111: Tony Motta | D111: tmotta@12news.com | E111: (407)461-5091 | F111: NBC-12News / Director of Sales | G111: Future | H111: Future | I111: 2026-27
A112: Scott | B112: Taggart | C112: Scott Taggart | D112: Scot92.Taggart@gmail.com | E112: (480) 392-4962 | F112: Director of Sales | G112: Future | H112: Future | I112: 2026-27
